topsis/__init__.py
topsis/__main__.py
topsis/cli.py
topsis/topsis.py
topsis_102216116-1.0.2.dist-info/METADATA
topsis_102216116-1.0.2.dist-info/WHEEL
topsis_102216116-1.0.2.dist-info/entry_points.txt
topsis_102216116-1.0.2.dist-info/top_level.txt
topsis_102216116-1.0.2.dist-info/RECORD
